mobio_dnc_sdk-1.0.2-py3.8-nspkg.pth
mobio/sdks/dnc/__init__.py
mobio/sdks/dnc/config.py
mobio/sdks/dnc/contact_spam_model.py
mobio/sdks/dnc/dnc_sdk.py
mobio/sdks/dnc/mongo_connection.py
mobio/sdks/dnc/utils.py
mobio_dnc_sdk-1.0.2.dist-info/METADATA
mobio_dnc_sdk-1.0.2.dist-info/WHEEL
mobio_dnc_sdk-1.0.2.dist-info/namespace_packages.txt
mobio_dnc_sdk-1.0.2.dist-info/top_level.txt
mobio_dnc_sdk-1.0.2.dist-info/RECORD
