Metadata-Version: 2.1
Name: mobio-dnc-sdk
Version: 1.0.2
Summary: mobio donotcall, mobio dnc
Home-page: https://github.com/mobiovn
Author: MOBIO
Author-email: contact@mobio.vn
License: MIT
Project-URL: Source, https://github.com/mobiovn
Keywords: mobio,dnc,contact spam
Classifier: Development Status :: 3 - Alpha
Classifier: Intended Audience :: Developers
Classifier: Topic :: Software Development :: Build Tools
Classifier: License :: OSI Approved :: MIT License
Classifier: Programming Language :: Python :: 3
Classifier: Programming Language :: Python :: 3.6
Classifier: Programming Language :: Python :: 3.7
Classifier: Programming Language :: Python :: 3.8
Classifier: Programming Language :: Python :: 3.9
Classifier: Programming Language :: Python :: 3 :: Only
Requires-Python: >=3
Requires-Dist: m-caching
Requires-Dist: m-singleton
Requires-Dist: redis
Requires-Dist: pymongo
